Verilog Projects/Universal Shift Register/MUX4to1.v
module MUX4to1 (input a,input b,input c, input d , input s0, input s1, output reg out);
    always @(*) begin
        case({s1,s0})
            2'b00: out=a;
            2'b01: out=b;
            2'b10: out=c;
            2'b11: out=d;
            default: out = 1'b0;
        endcase
    end
endmodule

Verilog Projects/PISO/DFF.v
module DFF (input D, input clk, output reg Q);
    always @(posedge clk) begin
        Q <= D;
    end
endmodule

Verilog Projects/Universal Shift Register/USR.v
module USR(input clk, input sel0,input sel1, input a0,input a1,input a2,input a3,output q0,output q1, output q2,output q3);
    wire [4:1] mux_out, dff_out;

    
    assign {q3,q2,q1,q0}=dff_out;

    DFF dff[4:1] (mux_out[4:1],{clk,clk,clk,clk},dff_out[4:1]);

    MUX4to1 mux1 (dff_out[1],1'b0,dff_out[2],a0,sel0,sel1,mux_out[1]);
    MUX4to1 mux2 (dff_out[2],dff_out[1],dff_out[3],a1,sel0,sel1,mux_out[2]);
    MUX4to1 mux3 (dff_out[3],dff_out[2],dff_out[4],a2,sel0,sel1,mux_out[3]);
    MUX4to1 mux4 (dff_out[4],dff_out[3],1'b0,a3,sel0,sel1,mux_out[4]);
endmodule

Verilog Projects/Universal Shift Register/USR_tb.v
`timescale 1ns / 1ps

module tb_USR;

    reg clk;
    reg sel0;
    reg sel1;
    reg a0, a1, a2, a3;

    wire q0, q1, q2, q3;

    USR uut (
        .clk(clk), 
        .sel0(sel0), 
        .sel1(sel1), 
        .a0(a0), .a1(a1), .a2(a2), .a3(a3),
        .q0(q0), .q1(q1), .q2(q2), .q3(q3)
    );


    initial begin
        clk = 0;
        forever #5 clk = ~clk; 
    end


    initial begin

        $dumpfile("usr_waveforms.vcd"); 
        $dumpvars(0, tb_USR);          
        

        sel1 = 0; sel0 = 0;
        a0 = 0; a1 = 0; a2 = 0; a3 = 0;

   
        #10; 
        

        $display("Time\t S1 S0\t A0A1A2A3\t Q0Q1Q2Q3\t Operation");
        $display("-------------------------------------------------------------------");

        // TEST 1: Parallel Load (S1=1, S0=1)
        // Let's load the pattern 1011
        sel1 = 1; sel0 = 1;
        a3 = 1; a2 = 0; a1 = 1; a0 = 1; 
        #10; 
        $display("%0t\t %b  %b \t %b%b%b%b\t\t %b%b%b%b\t\t Parallel Load", $time, sel1, sel0, a0, a1, a2, a3, q0, q1, q2, q3);

        // TEST 2: No Change (S1=0, S0=0)
        // Output should remain 1011
        sel1 = 0; sel0 = 0;
        #10;
        $display("%0t\t %b  %b \t %b%b%b%b\t\t %b%b%b%b\t\t No Change", $time, sel1, sel0, a0, a1, a2, a3, q0, q1, q2, q3);

        // TEST 3: Shift Right (S1=0, S0=1)
        sel1 = 0; sel0 = 1;
        #10; 
        $display("%0t\t %b  %b \t ----\t\t %b%b%b%b\t\t Shift Right 1", $time, sel1, sel0, q0, q1, q2, q3);
        #10; 
        $display("%0t\t %b  %b \t ----\t\t %b%b%b%b\t\t Shift Right 2", $time, sel1, sel0, q0, q1, q2, q3);

        // TEST 4: Parallel Load (resetting for left shift test)
        // Let's load 1101
        sel1 = 1; sel0 = 1;
        a3 = 1; a2 = 1; a1 = 0; a0 = 1; 
        #10;
        $display("%0t\t %b  %b \t %b%b%b%b\t\t %b%b%b%b\t\t Parallel Load", $time, sel1, sel0, a0, a1, a2, a3, q0, q1, q2, q3);

        // TEST 5: Shift Left (S1=1, S0=0)
        sel1 = 1; sel0 = 0;
        #10;
        $display("%0t\t %b  %b \t ----\t\t %b%b%b%b\t\t Shift Left 1", $time, sel1, sel0, q0, q1, q2, q3);
        #10;
        $display("%0t\t %b  %b \t ----\t\t %b%b%b%b\t\t Shift Left 2", $time, sel1, sel0, q0, q1, q2, q3);

        // Finish simulation
        #20;
        $finish;
    end
endmodule

Verilog Projects/Universal Shift Register/usr_waveforms.vcd
$date
	Wed Jul  1 16:03:00 2026
$end
$version
	Icarus Verilog
$end
$timescale
	1ps
$end
$scope module tb_USR $end
$var wire 1 ! q3 $end
$var wire 1 " q2 $end
$var wire 1 # q1 $end
$var wire 1 $ q0 $end
$var reg 1 % a0 $end
$var reg 1 & a1 $end
$var reg 1 ' a2 $end
$var reg 1 ( a3 $end
$var reg 1 ) clk $end
$var reg 1 * sel0 $end
$var reg 1 + sel1 $end
$scope module uut $end
$var wire 1 % a0 $end
$var wire 1 & a1 $end
$var wire 1 ' a2 $end
$var wire 1 ( a3 $end
$var wire 1 ) clk $end
$var wire 1 * sel0 $end
$var wire 1 + sel1 $end
$var wire 1 ! q3 $end
$var wire 1 " q2 $end
$var wire 1 # q1 $end
$var wire 1 $ q0 $end
$var wire 4 , mux_out [4:1] $end
$var wire 4 - dff_out [4:1] $end
$scope module dff[1] $end
$var wire 1 . D $end
$var wire 1 / clk $end
$var reg 1 0 Q $end
$upscope $end
$scope module dff[2] $end
$var wire 1 1 D $end
$var wire 1 2 clk $end
$var reg 1 3 Q $end
$upscope $end
$scope module dff[3] $end
$var wire 1 4 D $end
$var wire 1 5 clk $end
$var reg 1 6 Q $end
$upscope $end
$scope module dff[4] $end
$var wire 1 7 D $end
$var wire 1 8 clk $end
$var reg 1 9 Q $end
$upscope $end
$scope module mux1 $end
$var wire 1 : a $end
$var wire 1 ; b $end
$var wire 1 < c $end
$var wire 1 % d $end
$var wire 1 * s0 $end
$var wire 1 + s1 $end
$var reg 1 = out $end
$upscope $end
$scope module mux2 $end
$var wire 1 > a $end
$var wire 1 ? b $end
$var wire 1 @ c $end
$var wire 1 & d $end
$var wire 1 * s0 $end
$var wire 1 + s1 $end
$var reg 1 A out $end
$upscope $end
$scope module mux3 $end
$var wire 1 B a $end
$var wire 1 C b $end
$var wire 1 D c $end
$var wire 1 ' d $end
$var wire 1 * s0 $end
$var wire 1 + s1 $end
$var reg 1 E out $end
$upscope $end
$scope module mux4 $end
$var wire 1 F a $end
$var wire 1 G b $end
$var wire 1 H c $end
$var wire 1 ( d $end
$var wire 1 * s0 $end
$var wire 1 + s1 $end
$var reg 1 I out $end
$upscope $end
$upscope $end
$upscope $end
$enddefinitions $end
$comment Show the parameter values. $end
$dumpall
$end
#0
$dumpvars
xI
0H
xG
xF
xE
xD
xC
xB
xA
x@
x?
x>
x=
x<
0;
x:
x9
08
x7
x6
05
x4
x3
02
x1
x0
0/
x.
bx -
bx ,
0+
0*
0)
0(
0'
0&
0%
x$
x#
x"
x!
$end
#5000
1/
12
15
18
1)
#10000
17
04
11
1.
0/
02
05
08
b1011 ,
1=
1A
0E
1I
0)
1%
1&
1(
1*
1+
#15000
1:
1<
1>
1?
0@
0B
1C
1D
1F
0G
1!
0"
1#
1$
b1011 -
10
13
06
19
1/
12
15
18
1)
#20000
0/
02
05
08
0)
0*
0+
#25000
1/
12
15
18
1)
#30000
07
14
0.
0/
02
05
08
b110 ,
0=
1E
0I
0)
1*
#35000
17
01
b1100 ,
0A
1I
0:
0?
1@
1B
0D
0F
1G
0!
1"
0$
b110 -
00
16
09
1/
12
15
18
1)
#40000
0/
02
05
08
0)
#45000
04
b1000 ,
0E
0<
0>
0C
1D
1F
1!
0#
b1100 -
03
19
1/
12
15
18
1)
#50000
14
1.
0/
02
05
08
b1101 ,
1=
1E
0)
0&
1'
1+
#55000
1:
1?
1$
b1101 -
10
1/
12
15
18
1)
#60000
07
11
0.
0/
02
05
08
b110 ,
0=
1A
0I
0)
0*
#65000
04
1.
b11 ,
1=
0E
0:
1<
1>
0?
1C
0D
0F
0!
1#
0$
b110 -
00
13
09
1/
12
15
18
1)
#70000
0/
02
05
08
0)
#75000
01
b1 ,
0A
1:
1?
0@
0B
0G
0"
1$
b11 -
10
06
1/
12
15
18
1)
#80000
0/
02
05
08
0)
#85000
0.
b0 ,
0=
0<
0>
0C
0#
b1 -
03
1/
12
15
18
1)
#90000
0/
02
05
08
0)
#95000
0:
0?
0$
b0 -
00
1/
12
15
18
1)
