Verilog Projects/Divisibility 5 Checker/Mod_5_checker.v
module Mod_5_FSM (
    input      clk,
    input      reset,
    input      bit_in,
    output reg out);


    reg [2:0] current_state, next_state;

    parameter REM_0 = 3'b000; 
    parameter REM_1 = 3'b001; 
    parameter REM_2 = 3'b010; 
    parameter REM_3 = 3'b011; 
    parameter REM_4 = 3'b100; 

    always @(posedge clk or posedge reset) begin
        if (reset)
            current_state <= REM_0;
        else
            current_state <= next_state;
    end

    always @(*) begin
        case (current_state)
            REM_0: next_state = bit_in ? REM_1 : REM_0; 
            REM_1: next_state = bit_in ? REM_3 : REM_2; 
            REM_2: next_state = bit_in ? REM_0 : REM_4; 
            REM_3: next_state = bit_in ? REM_2 : REM_1; 
            REM_4: next_state = bit_in ? REM_4 : REM_3; 
            default: next_state = REM_0;
        endcase
    end

    always @(*) begin
        if ((current_state == REM_0 && bit_in == 1'b0) || 
            (current_state == REM_2 && bit_in == 1'b1))
            out = 1'b1; 
        else
            out = 1'b0;
    end

endmodule

Verilog Projects/Divisibility 5 Checker/Mod_5_tb.v
`timescale 1ns / 1ps

// ========================================================
// Mealy Modulo 5 FSM Testbench
// Author: Ayush Bhushan (24EE10043)
// ========================================================

module tb_Mod_5_Mealy();

    reg clk;
    reg reset;
    reg bit_in;
    wire out;

    // Instantiate the Mealy FSM
    Mod_5_FSM uut (
        .clk(clk),
        .reset(reset),
        .bit_in(bit_in),
        .out(out)
    );

    // Clock generation
    always #5 clk = ~clk;

    initial begin
        clk = 0;
        reset = 1;
        bit_in = 0;
        
        $dumpfile("mod5_mealy.vcd");
        $dumpvars(0, tb_Mod_5_Mealy);

        #20;
        
        // ---------------------------------------------------------
        // Test Case 1: Number 25 (Binary: 11001)
        // ---------------------------------------------------------
        $display("\n--- Starting Test Case 1: Input = 25 (11001) ---");
        
        @(posedge clk);
        reset <= 0;
        bit_in <= 1; // MSB
        
        @(posedge clk) bit_in <= 1;
        @(posedge clk) bit_in <= 0;
        @(posedge clk) bit_in <= 0;
        @(posedge clk) bit_in <= 1; // LSB
        
        // In a Mealy machine, the output is valid DURING the clock cycle 
        // the final bit is applied, right before the next clock edge!
        #1; // Wait 1 time unit for combinational output logic to settle
        $display("Final Output for 25: %b (Expected: 1)", out);
        
        @(posedge clk); // Shift the final bit into the flip-flops

        // ---------------------------------------------------------
        // Reset Between Tests
        // ---------------------------------------------------------
        reset <= 1; 
        bit_in <= 0; 
        #10; 
        
        // ---------------------------------------------------------
        // Test Case 2: Number 14 (Binary: 1110)
        // ---------------------------------------------------------
        $display("\n--- Starting Test Case 2: Input = 14 (1110) ---");
        
        @(posedge clk);
        reset <= 0;
        bit_in <= 1; // MSB
        
        @(posedge clk) bit_in <= 1;
        @(posedge clk) bit_in <= 1;
        @(posedge clk) bit_in <= 0; // LSB
        
        #1; // Wait 1 time unit for combinational output logic to settle
        $display("Final Output for 14: %b (Expected: 0)\n", out);

        #20;
        $finish;
    end
    
    // Print only on the positive edge using $strobe
    always @(posedge clk) begin
        $strobe("Time=%0t | clk=%b | reset=%b | bit_in=%b || FSM State=%b | Mealy out=%b", 
                $time, clk, reset, bit_in, uut.current_state, out);
    end

endmodule

Verilog Projects/Divisibility 5 Checker/mod5_mealy.vcd
$date
	Mon Jun 29 15:35:09 2026
$end
$version
	Icarus Verilog
$end
$timescale
	1ps
$end
$scope module tb_Mod_5_Mealy $end
$var wire 1 ! out $end
$var reg 1 " bit_in $end
$var reg 1 # clk $end
$var reg 1 $ reset $end
$scope module uut $end
$var wire 1 " bit_in $end
$var wire 1 # clk $end
$var wire 1 $ reset $end
$var parameter 3 % REM_0 $end
$var parameter 3 & REM_1 $end
$var parameter 3 ' REM_2 $end
$var parameter 3 ( REM_3 $end
$var parameter 3 ) REM_4 $end
$var reg 3 * current_state [2:0] $end
$var reg 3 + next_state [2:0] $end
$var reg 1 ! out $end
$upscope $end
$upscope $end
$enddefinitions $end
$comment Show the parameter values. $end
$dumpall
b100 )
b11 (
b10 '
b1 &
b0 %
$end
#0
$dumpvars
b0 +
b0 *
1$
0#
0"
1!
$end
#5000
1#
#10000
0#
#15000
1#
#20000
0#
#25000
0!
b1 +
1"
0$
1#
#30000
0#
#35000
b11 +
b1 *
1#
#40000
0#
#45000
b1 +
b11 *
0"
1#
#50000
0#
#55000
b10 +
b1 *
1#
#60000
0#
#65000
1!
b0 +
b10 *
1"
1#
#70000
0#
#75000
b0 *
0"
1$
1#
#80000
0#
#85000
0!
b1 +
1"
0$
1#
#90000
0#
#95000
b11 +
b1 *
1#
#100000
0#
#105000
b10 +
b11 *
1#
#110000
0#
#115000
b100 +
b10 *
0"
1#
#120000
0#
#125000
b11 +
b100 *
1#
#130000
0#
#135000
b1 +
b11 *
1#
