Verilog Projects/PISO/MUX2to1.v
module MUX2to1 (input a,input b,input sel, output reg out);
    always @(*) begin
        case(sel)
            1'b0: out=a;
            1'b1: out=b;
            default: out = 1'b0;
        endcase
    end
endmodule

Verilog Projects/PISO/DFF.v
module DFF (input D, input clk, output reg Q);
    always @(posedge clk) begin
        Q <= D;
    end
endmodule

Verilog Projects/PISO/PISO.v
module PISO (input [0:3] A, input clk, input load, output out );
    wire [3:0] dff_out,mux_out;

    DFF dff[3:0] (mux_out[3:0],clk,dff_out[3:0]);
    assign out=dff_out[3];

    MUX2to1 mux0 (1'b0,A[0],load,mux_out[0]);
    MUX2to1 mux1 (dff_out[0],A[1],load,mux_out[1]);
    MUX2to1 mux2 (dff_out[1],A[2],load,mux_out[2]);
    MUX2to1 mux3 (dff_out[2],A[3],load,mux_out[3]);
endmodule

Verilog Projects/PISO/PISO_tb.v
`timescale 1ns / 1ps

module tb_PISO;

    // --- Inputs to UUT ---
    reg [0:3] A;
    reg clk;
    reg load;

    // --- Outputs from UUT ---
    wire out;

    // --- Instantiate the PISO module ---
    PISO uut (
        .A(A), 
        .clk(clk), 
        .load(load), 
        .out(out)
    );

    // --- Clock Generation ---
    always #5 clk = ~clk;

    // --- Test Stimulus ---
    initial begin
        $dumpfile("dump.vcd");       // Names the output waveform file
        $dumpvars(0, tb_PISO);

        clk = 0;
        load = 0;
        A = 4'b0000;
        #10;
        
        // TEST CASE 1: Load and shift 1011
        $display("\n--- Starting Test Case 1: Load 1011 ---");
        A = 4'b1011;  
        load = 1;     
        #10;          
        
        load = 0;     
        #40;          
        
        // TEST CASE 2: Load and shift 0110
        $display("\n--- Starting Test Case 2: Load 0110 ---");
        A = 4'b0110;  
        load = 1;     
        #10;          
        
        load = 0;     
        #40;          

        $display("\nSimulation Complete.");
        $finish;
    end
    
    // --- Signal Monitoring (UPDATED) ---
    // This will now ONLY print on the positive edge of the clock.
    // I also removed 'clk' from the print statement, since it will always be 1 here.
    always @(posedge clk) begin
        $display("Time = %0t | load = %b | A = %b | Serial Out = %b", 
                 $time, load, A, out);
    end

endmodule

Verilog Projects/PISO/dump.vcd
$date
	Mon Jun 29 00:35:00 2026
$end
$version
	Icarus Verilog
$end
$timescale
	1ps
$end
$scope module tb_PISO $end
$var wire 1 ! out $end
$var reg 4 " A [0:3] $end
$var reg 1 # clk $end
$var reg 1 $ load $end
$scope module uut $end
$var wire 4 % A [0:3] $end
$var wire 1 # clk $end
$var wire 1 $ load $end
$var wire 1 ! out $end
$var wire 4 & mux_out [3:0] $end
$var wire 4 ' dff_out [3:0] $end
$scope module dff[0] $end
$var wire 1 ( D $end
$var wire 1 # clk $end
$var reg 1 ) Q $end
$upscope $end
$scope module dff[1] $end
$var wire 1 * D $end
$var wire 1 # clk $end
$var reg 1 + Q $end
$upscope $end
$scope module dff[2] $end
$var wire 1 , D $end
$var wire 1 # clk $end
$var reg 1 - Q $end
$upscope $end
$scope module dff[3] $end
$var wire 1 . D $end
$var wire 1 # clk $end
$var reg 1 / Q $end
$upscope $end
$scope module mux0 $end
$var wire 1 0 a $end
$var wire 1 1 b $end
$var wire 1 $ sel $end
$var reg 1 2 out $end
$upscope $end
$scope module mux1 $end
$var wire 1 3 a $end
$var wire 1 4 b $end
$var wire 1 $ sel $end
$var reg 1 5 out $end
$upscope $end
$scope module mux2 $end
$var wire 1 6 a $end
$var wire 1 7 b $end
$var wire 1 $ sel $end
$var reg 1 8 out $end
$upscope $end
$scope module mux3 $end
$var wire 1 9 a $end
$var wire 1 : b $end
$var wire 1 $ sel $end
$var reg 1 ; out $end
$upscope $end
$upscope $end
$upscope $end
$enddefinitions $end
$comment Show the parameter values. $end
$dumpall
$end
#0
$dumpvars
x;
0:
x9
x8
07
x6
x5
04
x3
02
01
00
x/
x.
x-
x,
x+
x*
x)
0(
bx '
bx0 &
b0 %
0$
0#
b0 "
x!
$end
#5000
0*
bx00 &
05
03
bx0 '
0)
1#
#10000
1.
1,
1(
b1101 &
12
18
1;
11
17
1:
0#
1$
b1011 "
b1011 %
#15000
1!
13
06
19
b1101 '
1/
1-
0+
1)
1#
#20000
0,
1*
0(
b1010 &
02
15
08
0#
0$
#25000
0.
1,
0*
b100 &
05
18
0;
03
16
09
b1010 '
0)
1+
0-
1#
#30000
0#
#35000
1.
0,
b1000 &
08
1;
0!
06
19
b100 '
0/
1-
0+
1#
#40000
0#
#45000
0.
b0 &
0;
1!
09
b1000 '
0-
1/
1#
#50000
0#
#55000
0!
b0 '
0/
1#
#60000
1,
1*
b110 &
15
18
01
14
0:
0#
1$
b110 "
b110 %
#65000
16
19
b110 '
1+
1-
1#
#70000
1.
0*
b1100 &
05
1;
0#
0$
#75000
0,
b1000 &
08
1!
06
b1100 '
1/
0+
1#
#80000
0#
#85000
0.
b0 &
0;
09
b1000 '
0-
1#
#90000
0#
#95000
0!
b0 '
0/
1#
